{"id":"CFEAE703-93D7-433B-A4BF-027A91DE2445","validationEntity":{"analysedDataType":"auto","dataResult":{"createdDate":"2022-03-21T06:18:10Z"}},"modelEntity":{"createdDate":"2022-03-21T06:18:10Z","id":"98624C8F-4FCF-4E0F-933C-C12CB97A2C9F","experimentID":"CFEAE703-93D7-433B-A4BF-027A91DE2445","title":"","modifiedDate":"2022-03-21T06:18:10Z","preferredFilename":"","version":"1.0","modelURL":"Models\/cityRecommender.mlmodel\/"},"version":"1.0","settingEntity":{"augmentations":[],"rmUserColumn":"UA_Continent","suggestedColumns":["Business Freedom","Commute","Cost of Living","Economy","Education","Environmental Quality","Healthcare","Housing","Internet Access","Leisure & Culture","Outdoors","Safety","Startups","Taxation","Tolerance","Travel Connectivity","UA_Continent","UA_Country","UA_Name","Venture Capital","X1"],"seedType":"default","transferLearningEmbeddingType":"dynamic","handPoseClassifierAugmentations":[],"rmRatingColumn":"Leisure & Culture","algorithmType":"maxEnt","rmItemColumn":"UA_Name","taskType":"recommender","suggestedColumnValues":["","","","","","","","","","","","","","","","","","","","",""],"featureNames":[],"harVideoAugmentations":0,"handActionClassifierAugmentations":[],"suggestedColumnTypes":["Double","Double","Double","Double","Double","Double","Double","Double","Double","Int","Double","Double","Double","Double","Double","Double","String","String","String","Double","String"],"styleTransferAlgorithmType":"image"},"state":"trained","trainingEntity":{"finishTime":"2022-03-21T06:18:39Z","recipeTrainingResults":{"recommender":{"mAP":1,"metrics":[{"precision":1,"cutoff":1},{"precision":1,"cutoff":2},{"precision":1,"cutoff":3},{"precision":1,"cutoff":4},{"precision":1,"cutoff":5}]}},"dataResult":{"itemsCount":266,"createdDate":"2022-03-21T06:18:10Z","columns":["Business Freedom","Commute","Cost of Living","Economy","Education","Environmental Quality","Healthcare","Housing","Internet Access","Leisure & Culture","Outdoors","Safety","Startups","Taxation","Tolerance","Travel Connectivity","UA_Continent","UA_Country","UA_Name","Venture Capital","X1"],"dataURL":"file:\/\/\/Users\/carlos\/Downloads\/citiesRatedOutdoors.csv","classesCount":264,"dataSourceID":"3F73784E-B2B6-4643-8829-D807EF65422E","analysis":{"summary":{"sampleCount":266,"classCount":264,"canUseValidation":1},"issues":[]},"columnTypes":["Double","Double","Double","Double","Double","Double","Double","Double","Double","Int","Double","Double","Double","Double","Double","Double","String","String","String","Double","String"],"columnValues":["","","","","","","","","","","","","","","","","","","","",""]},"dataURL":"file:\/\/\/Users\/carlos\/Downloads\/citiesRatedOutdoors.csv","featureExtractionCheckpointMayBeAvailable":false,"progress":[],"trainingAccuracy":1,"checkpointMetrics":{},"analysedDataType":"none","dataSourceID":"3F73784E-B2B6-4643-8829-D807EF65422E","snapshottableCheckpoints":{},"startTime":"2022-03-21T06:18:38Z"},"createdDate":"2022-03-21T06:18:10Z","evaluationContainerEntity":{"testingEvaluationEntity":{"id":"5afc0fb7-c348-4e87-9dce-112ad4ae0860","createdDate":"2022-03-21T06:18:10Z","dataResult":{"createdDate":"2022-03-21T06:18:10Z"},"analysedDataType":"none"},"createdDate":"2022-03-21T06:54:35Z","id":"eecf766c-b623-4925-982d-e5202469a857","trainingEvaluationEntity":{"result":{"recommender":{"mAP":1,"metrics":[{"precision":1,"cutoff":1},{"precision":1,"cutoff":2},{"precision":1,"cutoff":3},{"precision":1,"cutoff":4},{"precision":1,"cutoff":5}]}},"createdDate":"2022-03-21T06:18:10Z","id":"9c7846c8-f17f-4dca-90cc-b801ddfe6257","dataURL":"file:\/\/\/Users\/carlos\/Downloads\/citiesRatedOutdoors.csv","dataSourceID":"3F73784E-B2B6-4643-8829-D807EF65422E","dataResult":{"itemsCount":266,"createdDate":"2022-03-21T06:18:10Z","dataURL":"file:\/\/\/Users\/carlos\/Downloads\/citiesRatedOutdoors.csv","dataSourceID":"3F73784E-B2B6-4643-8829-D807EF65422E","classesCount":264,"analysis":{"summary":{"sampleCount":266,"classCount":264,"canUseValidation":1},"issues":[]}},"analysedDataType":"none"},"previewType":"recommender","modifiedDate":"2022-03-21T06:54:35Z","validationEvaluationEntity":{"id":"752b2a0b-63b9-4043-abcd-906e1d41b68f","createdDate":"2022-03-21T06:18:10Z","dataResult":{"createdDate":"2022-03-21T06:18:10Z"},"analysedDataType":"auto"},"evaluationEntities":[{"id":"770be0dd-8aef-42df-8507-2b011588e5a0","createdDate":"2022-03-21T06:37:38Z","dataResult":{"createdDate":"2022-03-21T06:40:35Z"},"analysedDataType":"none"}]},"evaluationEntities":[],"activityEntities":["trainingStarted",[{"id":"9A304E10-BF19-42DF-99AC-508113CB6217","title":"Training Started","createdDate":"2022-03-21T06:18:38Z","event":"trainingStarted","subtitle":"cityRecommender"}],"experimentCreated",[{"id":"AC5D0324-7E0C-4857-8C8D-C35D7B548FE1","title":"Model Source Created","createdDate":"2022-03-21T06:18:10Z","event":"experimentCreated","subtitle":"cityRecommender"}],"trainingFinished",[{"id":"4FE41E52-DDD1-4E38-9DC4-16366EDB3554","title":"Training Completed","createdDate":"2022-03-21T06:18:39Z","event":"trainingFinished","subtitle":"cityRecommender"}],"trainingDataAdded",[{"id":"FE1EC471-8AC6-43A5-A681-994494BCF26A","title":"Training Data Added","createdDate":"2022-03-21T06:18:18Z","event":"trainingDataAdded","subtitle":"citiesRatedOutdoors.csv"}]],"title":"cityRecommender 2","evaluationEntity":{"id":"18caa9d9-b8b4-41fb-834d-101323050f5a","createdDate":"2022-03-21T06:18:10Z","dataResult":{"createdDate":"2022-03-21T06:18:10Z"},"analysedDataType":"none"},"evaluationState":"uninitialized","snapshotRole":{"withoutSnapshots":0},"modifiedDate":"2022-03-21T06:54:35Z","contentDataResult":{"createdDate":"2022-03-21T06:18:10Z"},"preferredFilename":"cityRecommender"}